autoXAS/__init__.py
autoXAS/autoXAS.py
autoxas-1.0.2.dist-info/licenses/LICENSE
autoxas-1.0.2.dist-info/METADATA
autoxas-1.0.2.dist-info/WHEEL
autoxas-1.0.2.dist-info/top_level.txt
autoxas-1.0.2.dist-info/RECORD
