Metadata-Version: 2.4
Name: autoXAS
Version: 1.0.2
Summary: A package for automating the data processing involved in the analysis of (in-situ) X-ray absorption spectroscopy data.
Author-email: Ulrik Friis-Jensen <ufj@chem.ku.dk>
License:                                  Apache License
Project-URL: Homepage, https://github.com/UlrikFriisJensen/autoXAS
Project-URL: Documentation, https://autoxas.readthedocs.io/en/latest/
Project-URL: Source, https://github.com/UlrikFriisJensen/autoXAS/tree/main/autoXAS
Project-URL: Bug Tracker, https://github.com/UlrikFriisJensen/autoXAS/issues
Classifier: Programming Language :: Python :: 3
Classifier: Operating System :: OS Independent
Requires-Python: >=3.7
License-File: LICENSE
Requires-Dist: numpy
Requires-Dist: pandas>=1.5.0
Requires-Dist: xraylarch
Requires-Dist: matplotlib
Requires-Dist: plotly
Requires-Dist: plotly.express
Requires-Dist: seaborn
Requires-Dist: lmfit>=1.0.0
Requires-Dist: scikit-learn
Requires-Dist: tqdm
Requires-Dist: jupyter
Dynamic: license-file
